MANIFEST.in
README.md
setup.py
prehashed/__init__.py
prehashed/prehashed.py
prehashed.egg-info/PKG-INFO
prehashed.egg-info/SOURCES.txt
prehashed.egg-info/dependency_links.txt
prehashed.egg-info/requires.txt
prehashed.egg-info/top_level.txt