Metadata-Version: 2.1
Name: prehashed
Version: 1.0.1
Summary: Prehashing keys for memory saving.
Home-page: https://github.com/blester125/prehashed
Author: blester125
Author-email: blester125@gmail.com
License: MIT
Download-URL: https://github.com/blester125/prehashed/archive/1.0.1.tar.gz
Platform: UNKNOWN
Classifier: Intended Audience :: Developers
Classifier: Intended Audience :: Science/Research
Classifier: Development Status :: 3 - Alpha
Classifier: Programming Language :: Python :: 3 :: Only
Classifier: License :: OSI Approved :: MIT License
Classifier: Natural Language :: English
Classifier: Topic :: Scientific/Engineering
Classifier: Environment :: Console
Requires-Python: >=3.6
Provides-Extra: test
